{
  "document": {
    "id": "20:388",
    "name": "Body",
    "type": "FRAME",
    "scrollBehavior": "SCROLLS",
    "children": [
      {
        "id": "20:389",
        "name": "Container",
        "type": "FRAME",
        "scrollBehavior": "SCROLLS",
        "children": [
          {
            "id": "20:390",
            "name": "Image (全息机器人背景)",
            "type": "FRAME",
            "scrollBehavior": "SCROLLS",
            "rotation": 3.141592653589793,
            "children": [],
            "blendMode": "PASS_THROUGH",
            "clipsContent": true,
            "background": [
              {
                "blendMode": "NORMAL",
                "type": "IMAGE",
                "scaleMode": "FILL",
                "imageRef": "b4124542061a73722c53595a57823103fe6290fc"
              }
            ],
            "fills": [
              {
                "blendMode": "NORMAL",
                "type": "IMAGE",
                "scaleMode": "FILL",
                "imageRef": "b4124542061a73722c53595a57823103fe6290fc"
              }
            ],
            "strokes": [],
            "strokeWeight": 1.0,
            "strokeAlign": "INSIDE",
            "backgroundColor": {
              "r": 0.0,
              "g": 0.0,
              "b": 0.0,
              "a": 0.0
            },
            "absoluteBoundingBox": {
              "x": 0.0,
              "y": 0.0,
              "width": 1106.0,
              "height": 778.0
            },
            "absoluteRenderBounds": {
              "x": 0.0,
              "y": 0.0,
              "width": 1106.0,
              "height": 778.0
            },
            "constraints": {
              "vertical": "TOP",
              "horizontal": "LEFT"
            },
            "effects": [],
            "interactions": [],
            "complexStrokeProperties": {
              "strokeType": "BASIC"
            }
          },
          {
            "id": "20:391",
            "name": "Container",
            "type": "FRAME",
            "scrollBehavior": "SCROLLS",
            "children": [],
            "blendMode": "PASS_THROUGH",
            "clipsContent": false,
            "background": [],
            "fills": [],
            "strokes": [
              {
                "opacity": 0.44999998807907104,
                "blendMode": "NORMAL",
                "type": "SOLID",
                "color": {
                  "r": 0.21960784494876862,
                  "g": 0.545098066329956,
                  "b": 0.9921568632125854,
                  "a": 1.0
                }
              }
            ],
            "strokeWeight": 1.0,
            "individualStrokeWeights": {
              "top": 1.3333300352096558,
              "right": 0.0,
              "bottom": 0.0,
              "left": 1.3333300352096558
            },
            "strokeAlign": "INSIDE",
            "backgroundColor": {
              "r": 0.0,
              "g": 0.0,
              "b": 0.0,
              "a": 0.0
            },
            "absoluteBoundingBox": {
              "x": 16.0,
              "y": 16.0,
              "width": 20.0,
              "height": 20.0
            },
            "absoluteRenderBounds": {
              "x": 16.0,
              "y": 16.0,
              "width": 20.0,
              "height": 20.0
            },
            "constraints": {
              "vertical": "TOP",
              "horizontal": "LEFT"
            },
            "effects": [],
            "interactions": [],
            "complexStrokeProperties": {
              "strokeType": "BASIC"
            }
          },
          {
            "id": "20:392",
            "name": "Container",
            "type": "FRAME",
            "scrollBehavior": "SCROLLS",
            "children": [],
            "blendMode": "PASS_THROUGH",
            "clipsContent": false,
            "background": [],
            "fills": [],
            "strokes": [
              {
                "opacity": 0.44999998807907104,
                "blendMode": "NORMAL",
                "type": "SOLID",
                "color": {
                  "r": 0.21960784494876862,
                  "g": 0.545098066329956,
                  "b": 0.9921568632125854,
                  "a": 1.0
                }
              }
            ],
            "strokeWeight": 1.0,
            "individualStrokeWeights": {
              "top": 1.3333300352096558,
              "right": 1.3333300352096558,
              "bottom": 0.0,
              "left": 0.0
            },
            "strokeAlign": "INSIDE",
            "backgroundColor": {
              "r": 0.0,
              "g": 0.0,
              "b": 0.0,
              "a": 0.0
            },
            "absoluteBoundingBox": {
              "x": 1070.0,
              "y": 16.0,
              "width": 20.0,
              "height": 20.0
            },
            "absoluteRenderBounds": {
              "x": 1070.0,
              "y": 16.0,
              "width": 20.0,
              "height": 20.0
            },
            "constraints": {
              "vertical": "TOP",
              "horizontal": "LEFT"
            },
            "effects": [],
            "interactions": [],
            "complexStrokeProperties": {
              "strokeType": "BASIC"
            }
          },
          {
            "id": "20:393",
            "name": "Container",
            "type": "FRAME",
            "scrollBehavior": "SCROLLS",
            "children": [],
            "blendMode": "PASS_THROUGH",
            "clipsContent": false,
            "background": [],
            "fills": [],
            "strokes": [
              {
                "opacity": 0.44999998807907104,
                "blendMode": "NORMAL",
                "type": "SOLID",
                "color": {
                  "r": 0.21960784494876862,
                  "g": 0.545098066329956,
                  "b": 0.9921568632125854,
                  "a": 1.0
                }
              }
            ],
            "strokeWeight": 1.0,
            "individualStrokeWeights": {
              "top": 0.0,
              "right": 0.0,
              "bottom": 1.3333300352096558,
              "left": 1.3333300352096558
            },
            "strokeAlign": "INSIDE",
            "backgroundColor": {
              "r": 0.0,
              "g": 0.0,
              "b": 0.0,
              "a": 0.0
            },
            "absoluteBoundingBox": {
              "x": 16.0,
              "y": 742.0,
              "width": 20.0,
              "height": 20.0
            },
            "absoluteRenderBounds": {
              "x": 16.0,
              "y": 742.0,
              "width": 20.0,
              "height": 20.0
            },
            "constraints": {
              "vertical": "TOP",
              "horizontal": "LEFT"
            },
            "effects": [],
            "interactions": [],
            "complexStrokeProperties": {
              "strokeType": "BASIC"
            }
          },
          {
            "id": "20:394",
            "name": "Container",
            "type": "FRAME",
            "scrollBehavior": "SCROLLS",
            "children": [],
            "blendMode": "PASS_THROUGH",
            "clipsContent": false,
            "background": [],
            "fills": [],
            "strokes": [
              {
                "opacity": 0.44999998807907104,
                "blendMode": "NORMAL",
                "type": "SOLID",
                "color": {
                  "r": 0.21960784494876862,
                  "g": 0.545098066329956,
                  "b": 0.9921568632125854,
                  "a": 1.0
                }
              }
            ],
            "strokeWeight": 1.0,
            "individualStrokeWeights": {
              "top": 0.0,
              "right": 1.3333300352096558,
              "bottom": 1.3333300352096558,
              "left": 0.0
            },
            "strokeAlign": "INSIDE",
            "backgroundColor": {
              "r": 0.0,
              "g": 0.0,
              "b": 0.0,
              "a": 0.0
            },
            "absoluteBoundingBox": {
              "x": 1070.0,
              "y": 742.0,
              "width": 20.0,
              "height": 20.0
            },
            "absoluteRenderBounds": {
              "x": 1070.0,
              "y": 742.0,
              "width": 20.0,
              "height": 20.0
            },
            "constraints": {
              "vertical": "TOP",
              "horizontal": "LEFT"
            },
            "effects": [],
            "interactions": [],
            "complexStrokeProperties": {
              "strokeType": "BASIC"
            }
          },
          {
            "id": "20:395",
            "name": "Container",
            "type": "FRAME",
            "scrollBehavior": "SCROLLS",
            "children": [
              {
                "id": "20:396",
                "name": "Image (源策未来 Logo)",
                "type": "FRAME",
                "scrollBehavior": "SCROLLS",
                "children": [],
                "blendMode": "PASS_THROUGH",
                "clipsContent": true,
                "background": [
                  {
                    "blendMode": "NORMAL",
                    "visible": false,
                    "type": "IMAGE",
                    "scaleMode": "FIT",
                    "imageRef": "6ee0485127206ca46227e2e85c0f0cf33fa3da8d"
                  },
                  {
                    "blendMode": "NORMAL",
                    "type": "IMAGE",
                    "scaleMode": "FIT",
                    "imageRef": "5c2095ef7a841a423162b2864f0e943593e863aa"
                  }
                ],
                "fills": [
                  {
                    "blendMode": "NORMAL",
                    "visible": false,
                    "type": "IMAGE",
                    "scaleMode": "FIT",
                    "imageRef": "6ee0485127206ca46227e2e85c0f0cf33fa3da8d"
                  },
                  {
                    "blendMode": "NORMAL",
                    "type": "IMAGE",
                    "scaleMode": "FIT",
                    "imageRef": "5c2095ef7a841a423162b2864f0e943593e863aa"
                  }
                ],
                "strokes": [],
                "strokeWeight": 1.0,
                "strokeAlign": "INSIDE",
                "backgroundColor": {
                  "r": 0.0,
                  "g": 0.0,
                  "b": 0.0,
                  "a": 0.0
                },
                "absoluteBoundingBox": {
                  "x": 40.0,
                  "y": 32.0,
                  "width": 44.0,
                  "height": 44.0
                },
                "absoluteRenderBounds": {
                  "x": 40.0,
                  "y": 32.0,
                  "width": 44.0,
                  "height": 44.0
                },
                "constraints": {
                  "vertical": "TOP",
                  "horizontal": "LEFT"
                },
                "layoutAlign": "INHERIT",
                "layoutGrow": 0.0,
                "layoutSizingHorizontal": "FIXED",
                "layoutSizingVertical": "FIXED",
                "effects": [],
                "interactions": [],
                "complexStrokeProperties": {
                  "strokeType": "BASIC"
                }
              },
              {
                "id": "20:397",
                "name": "Text",
                "type": "FRAME",
                "scrollBehavior": "SCROLLS",
                "children": [
                  {
                    "id": "20:398",
                    "name": "源策未来",
                    "type": "TEXT",
                    "scrollBehavior": "SCROLLS",
                    "blendMode": "PASS_THROUGH",
                    "fills": [
                      {
                        "blendMode": "NORMAL",
                        "type": "SOLID",
                        "color": {
                          "r": 0.9098039269447327,
                          "g": 0.95686274766922,
                          "b": 1.0,
                          "a": 1.0
                        }
                      }
                    ],
                    "strokes": [],
                    "strokeWeight": 1.0,
                    "strokeAlign": "OUTSIDE",
                    "absoluteBoundingBox": {
                      "x": 96.0,
                      "y": 38.0,
                      "width": 91.0,
                      "height": 30.0
                    },
                    "absoluteRenderBounds": {
                      "x": 96.55999755859375,
                      "y": 42.86000061035156,
                      "width": 89.760009765625,
                      "height": 18.939998626708984
                    },
                    "constraints": {
                      "vertical": "TOP",
                      "horizontal": "LEFT"
                    },
                    "characters": "源策未来",
                    "characterStyleOverrides": [],
                    "styleOverrideTable": {},
                    "lineTypes": [
                      "NONE"
                    ],
                    "lineIndentations": [
                      0
                    ],
                    "style": {
                      "fontFamily": "Inter",
                      "fontPostScriptName": null,
                      "fontStyle": "Bold",
                      "fontWeight": 700,
                      "textAutoResize": "WIDTH_AND_HEIGHT",
                      "fontSize": 20.0,
                      "textAlignHorizontal": "LEFT",
                      "textAlignVertical": "TOP",
                      "letterSpacing": 3.5999999046325684,
                      "lineHeightPx": 30.0,
                      "lineHeightPercent": 123.94367218017578,
                      "lineHeightPercentFontSize": 150.0,
                      "lineHeightUnit": "PIXELS"
                    },
                    "layoutVersion": 5,
                    "effects": [],
                    "interactions": [],
                    "complexStrokeProperties": {
                      "strokeType": "BASIC"
                    }
                  }
                ],
                "blendMode": "PASS_THROUGH",
                "clipsContent": false,
                "background": [],
                "fills": [],
                "strokes": [],
                "strokeWeight": 1.0,
                "strokeAlign": "INSIDE",
                "backgroundColor": {
                  "r": 0.0,
                  "g": 0.0,
                  "b": 0.0,
                  "a": 0.0
                },
                "absoluteBoundingBox": {
                  "x": 96.0,
                  "y": 39.0,
                  "width": 94.40625,
                  "height": 30.0
                },
                "absoluteRenderBounds": {
                  "x": 96.0,
                  "y": 39.0,
                  "width": 94.40625,
                  "height": 30.0
                },
                "constraints": {
                  "vertical": "TOP",
                  "horizontal": "LEFT"
                },
                "layoutAlign": "INHERIT",
                "layoutGrow": 0.0,
                "layoutSizingHorizontal": "FIXED",
                "layoutSizingVertical": "FIXED",
                "effects": [],
                "interactions": [],
                "complexStrokeProperties": {
                  "strokeType": "BASIC"
                }
              }
            ],
            "blendMode": "PASS_THROUGH",
            "clipsContent": false,
            "background": [],
            "fills": [],
            "strokes": [],
            "strokeWeight": 1.0,
            "strokeAlign": "INSIDE",
            "backgroundColor": {
              "r": 0.0,
              "g": 0.0,
              "b": 0.0,
              "a": 0.0
            },
            "layoutMode": "HORIZONTAL",
            "counterAxisAlignItems": "CENTER",
            "strokesIncludedInLayout": true,
            "itemSpacing": 12.0,
            "layoutWrap": "NO_WRAP",
            "absoluteBoundingBox": {
              "x": 40.0,
              "y": 32.0,
              "width": 150.40625,
              "height": 44.0
            },
            "absoluteRenderBounds": {
              "x": 40.0,
              "y": 32.0,
              "width": 150.40625,
              "height": 44.0
            },
            "constraints": {
              "vertical": "TOP",
              "horizontal": "LEFT"
            },
            "layoutSizingHorizontal": "HUG",
            "layoutSizingVertical": "HUG",
            "effects": [],
            "interactions": [],
            "complexStrokeProperties": {
              "strokeType": "BASIC"
            }
          },
          {
            "id": "20:399",
            "name": "Form",
            "type": "FRAME",
            "scrollBehavior": "SCROLLS",
            "children": [
              {
                "id": "20:400",
                "name": "Container",
                "type": "FRAME",
                "scrollBehavior": "SCROLLS",
                "children": [
                  {
                    "id": "20:401",
                    "name": "Text",
                    "type": "FRAME",
                    "scrollBehavior": "SCROLLS",
                    "children": [
                      {
                        "id": "20:402",
                        "name": "用户名",
                        "type": "TEXT",
                        "scrollBehavior": "SCROLLS",
                        "blendMode": "PASS_THROUGH",
                        "fills": [
                          {
                            "opacity": 0.8500000238418579,
                            "blendMode": "NORMAL",
                            "type": "SOLID",
                            "color": {
                              "r": 0.5764706134796143,
                              "g": 0.772549033164978,
                              "b": 0.9921568632125854,
                              "a": 1.0
                            }
                          }
                        ],
                        "strokes": [],
                        "strokeWeight": 1.0,
                        "strokeAlign": "OUTSIDE",
                        "absoluteBoundingBox": {
                          "x": 361.90625,
                          "y": 240.33334350585938,
                          "width": 62.0,
                          "height": 23.0
                        },
                        "absoluteRenderBounds": {
                          "x": 363.0262451171875,
                          "y": 242.433349609375,
                          "width": 58.6400146484375,
                          "height": 18.6199951171875
                        },
                        "constraints": {
                          "vertical": "TOP",
                          "horizontal": "LEFT"
                        },
                        "characters": "用户名",
                        "characterStyleOverrides": [],
                        "styleOverrideTable": {},
                        "lineTypes": [
                          "NONE"
                        ],
                        "lineIndentations": [
                          0
                        ],
                        "style": {
                          "fontFamily": "Inter",
                          "fontPostScriptName": null,
                          "fontStyle": "Regular",
                          "fontWeight": 400,
                          "textAutoResize": "WIDTH_AND_HEIGHT",
                          "fontSize": 20.0,
                          "textAlignHorizontal": "RIGHT",
                          "textAlignVertical": "TOP",
                          "letterSpacing": 0.7599999904632568,
                          "lineHeightPx": 22.799999237060547,
                          "lineHeightPercent": 94.19718170166016,
                          "lineHeightPercentFontSize": 114.0,
                          "lineHeightUnit": "PIXELS"
                        },
                        "layoutVersion": 5,
                        "effects": [],
                        "interactions": [],
                        "complexStrokeProperties": {
                          "strokeType": "BASIC"
                        }
                      }
                    ],
                    "blendMode": "PASS_THROUGH",
                    "clipsContent": false,
                    "background": [],
                    "fills": [],
                    "strokes": [],
                    "strokeWeight": 1.0,
                    "strokeAlign": "INSIDE",
                    "backgroundColor": {
                      "r": 0.0,
                      "g": 0.0,
                      "b": 0.0,
                      "a": 0.0
                    },
                    "absoluteBoundingBox": {
                      "x": 363.0,
                      "y": 241.0,
                      "width": 60.79999923706055,
                      "height": 22.791667938232422
                    },
                    "absoluteRenderBounds": {
                      "x": 363.0,
                      "y": 241.0,
                      "width": 60.79999923706055,
                      "height": 22.791667938232422
                    },
                    "constraints": {
                      "vertical": "TOP",
                      "horizontal": "LEFT"
                    },
                    "layoutAlign": "INHERIT",
                    "layoutGrow": 0.0,
                    "minWidth": 60.79999923706055,
                    "layoutSizingHorizontal": "FIXED",
                    "layoutSizingVertical": "FIXED",
                    "effects": [],
                    "interactions": [],
                    "complexStrokeProperties": {
                      "strokeType": "BASIC"
                    }
                  },
                  {
                    "id": "20:403",
                    "name": "Container",
                    "type": "FRAME",
                    "scrollBehavior": "SCROLLS",
                    "children": [
                      {
                        "id": "20:404",
                        "name": "Text Input",
                        "type": "FRAME",
                        "scrollBehavior": "SCROLLS",
                        "children": [
                          {
                            "id": "20:405",
                            "name": "请输入用户名",
                            "type": "TEXT",
                            "scrollBehavior": "SCROLLS",
                            "blendMode": "PASS_THROUGH",
                            "fills": [
                              {
                                "opacity": 0.25,
                                "blendMode": "NORMAL",
                                "type": "SOLID",
                                "color": {
                                  "r": 0.5568627715110779,
                                  "g": 0.772549033164978,
                                  "b": 1.0,
                                  "a": 1.0
                                }
                              }
                            ],
                            "strokes": [],
                            "strokeWeight": 1.0,
                            "strokeAlign": "OUTSIDE",
                            "absoluteBoundingBox": {
                              "x": 452.4666442871094,
                              "y": 242.89584350585938,
                              "width": 273.8666687011719,
                              "height": 19.0
                            },
                            "absoluteRenderBounds": {
                              "x": 453.1386413574219,
                              "y": 244.37583923339844,
                              "width": 93.53598022460938,
                              "height": 14.896011352539062
                            },
                            "constraints": {
                              "vertical": "TOP",
                              "horizontal": "LEFT"
                            },
                            "layoutAlign": "STRETCH",
                            "layoutGrow": 0.0,
                            "layoutSizingHorizontal": "FILL",
                            "layoutSizingVertical": "HUG",
                            "characters": "请输入用户名",
                            "characterStyleOverrides": [],
                            "styleOverrideTable": {},
                            "lineTypes": [
                              "NONE"
                            ],
                            "lineIndentations": [
                              0
                            ],
                            "style": {
                              "fontFamily": "Inter",
                              "fontPostScriptName": null,
                              "fontStyle": "Regular",
                              "fontWeight": 400,
                              "textAutoResize": "HEIGHT",
                              "fontSize": 16.0,
                              "textAlignHorizontal": "LEFT",
                              "textAlignVertical": "TOP",
                              "letterSpacing": 0.0,
                              "lineHeightPx": 19.363636016845703,
                              "lineHeightPercent": 100.0,
                              "lineHeightUnit": "INTRINSIC_%"
                            },
                            "layoutVersion": 5,
                            "effects": [],
                            "interactions": [],
                            "complexStrokeProperties": {
                              "strokeType": "BASIC"
                            }
                          }
                        ],
                        "blendMode": "PASS_THROUGH",
                        "clipsContent": true,
                        "background": [],
                        "fills": [],
                        "strokes": [],
                        "strokeWeight": 1.0,
                        "strokeAlign": "INSIDE",
                        "backgroundColor": {
                          "r": 0.0,
                          "g": 0.0,
                          "b": 0.0,
                          "a": 0.0
                        },
                        "layoutMode": "VERTICAL",
                        "counterAxisSizingMode": "FIXED",
                        "primaryAxisSizingMode": "FIXED",
                        "primaryAxisAlignItems": "CENTER",
                        "strokesIncludedInLayout": true,
                        "layoutWrap": "NO_WRAP",
                        "absoluteBoundingBox": {
                          "x": 452.4666442871094,
                          "y": 240.39584350585938,
                          "width": 273.8666687011719,
                          "height": 24.0
                        },
                        "absoluteRenderBounds": {
                          "x": 452.4666442871094,
                          "y": 240.39584350585938,
                          "width": 273.8666687011719,
                          "height": 24.0
                        },
                        "constraints": {
                          "vertical": "TOP",
                          "horizontal": "LEFT"
                        },
                        "layoutAlign": "INHERIT",
                        "layoutGrow": 273.875,
                        "layoutSizingHorizontal": "FILL",
                        "layoutSizingVertical": "FIXED",
                        "effects": [],
                        "interactions": [],
                        "complexStrokeProperties": {
                          "strokeType": "BASIC"
                        }
                      }
                    ],
                    "blendMode": "PASS_THROUGH",
                    "clipsContent": false,
                    "background": [
                      {
                        "opacity": 0.25,
                        "blendMode": "NORMAL",
                        "type": "SOLID",
                        "color": {
                          "r": 0.03921568766236305,
                          "g": 0.11764705926179886,
                          "b": 0.27450981736183167,
                          "a": 1.0
                        }
                      }
                    ],
                    "fills": [
                      {
                        "opacity": 0.25,
                        "blendMode": "NORMAL",
                        "type": "SOLID",
                        "color": {
                          "r": 0.03921568766236305,
                          "g": 0.11764705926179886,
                          "b": 0.27450981736183167,
                          "a": 1.0
                        }
                      }
                    ],
                    "strokes": [
                      {
                        "opacity": 0.44999998807907104,
                        "blendMode": "NORMAL",
                        "type": "SOLID",
                        "color": {
                          "r": 0.21960784494876862,
                          "g": 0.545098066329956,
                          "b": 0.9921568632125854,
                          "a": 1.0
                        }
                      }
                    ],
                    "cornerRadius": 10.0,
                    "cornerSmoothing": 0.0,
                    "strokeWeight": 0.6666669845581055,
                    "strokeAlign": "INSIDE",
                    "backgroundColor": {
                      "r": 0.03921568766236305,
                      "g": 0.11764705926179886,
                      "b": 0.27450981736183167,
                      "a": 0.25
                    },
                    "layoutMode": "HORIZONTAL",
                    "primaryAxisSizingMode": "FIXED",
                    "counterAxisAlignItems": "CENTER",
                    "paddingLeft": 16.0,
                    "paddingRight": 16.0,
                    "paddingTop": 16.0,
                    "paddingBottom": 16.0,
                    "strokesIncludedInLayout": true,
                    "layoutWrap": "NO_WRAP",
                    "absoluteBoundingBox": {
                      "x": 435.79998779296875,
                      "y": 223.7291717529297,
                      "width": 307.20001220703125,
                      "height": 57.333335876464844
                    },
                    "absoluteRenderBounds": {
                      "x": 427.79998779296875,
                      "y": 215.7291717529297,
                      "width": 323.20001220703125,
                      "height": 73.33332824707031
                    },
                    "constraints": {
                      "vertical": "TOP",
                      "horizontal": "LEFT"
                    },
                    "layoutAlign": "INHERIT",
                    "layoutGrow": 307.2083435058594,
                    "layoutSizingHorizontal": "FILL",
                    "layoutSizingVertical": "HUG",
                    "effects": [
                      {
                        "type": "INNER_SHADOW",
                        "visible": true,
                        "color": {
                          "r": 0.21960784494876862,
                          "g": 0.545098066329956,
                          "b": 0.9921568632125854,
                          "a": 0.05000000074505806
                        },
                        "blendMode": "NORMAL",
                        "offset": {
                          "x": 0.0,
                          "y": 0.0
                        },
                        "radius": 12.0
                      },
                      {
                        "type": "DROP_SHADOW",
                        "visible": true,
                        "color": {
                          "r": 0.21960784494876862,
                          "g": 0.545098066329956,
                          "b": 0.9921568632125854,
                          "a": 0.11999999731779099
                        },
                        "blendMode": "NORMAL",
                        "offset": {
                          "x": 0.0,
                          "y": 0.0
                        },
                        "radius": 8.0,
                        "showShadowBehindNode": false
                      }
                    ],
                    "interactions": [],
                    "complexStrokeProperties": {
                      "strokeType": "BASIC"
                    }
                  }
                ],
                "blendMode": "PASS_THROUGH",
                "clipsContent": false,
                "background": [],
                "fills": [],
                "strokes": [],
                "strokeWeight": 1.0,
                "strokeAlign": "INSIDE",
                "backgroundColor": {
                  "r": 0.0,
                  "g": 0.0,
                  "b": 0.0,
                  "a": 0.0
                },
                "layoutMode": "HORIZONTAL",
                "primaryAxisSizingMode": "FIXED",
                "counterAxisAlignItems": "CENTER",
                "strokesIncludedInLayout": true,
                "itemSpacing": 12.0,
                "layoutWrap": "NO_WRAP",
                "absoluteBoundingBox": {
                  "x": 363.0,
                  "y": 223.7291717529297,
                  "width": 380.0,
                  "height": 57.333335876464844
                },
                "absoluteRenderBounds": {
                  "x": 363.0,
                  "y": 215.7291717529297,
                  "width": 388.0,
                  "height": 73.33332824707031
                },
                "constraints": {
                  "vertical": "TOP",
                  "horizontal": "LEFT"
                },
                "layoutAlign": "STRETCH",
                "layoutGrow": 0.0,
                "layoutSizingHorizontal": "FILL",
                "layoutSizingVertical": "HUG",
                "effects": [],
                "interactions": [],
                "complexStrokeProperties": {
                  "strokeType": "BASIC"
                }
              },
              {
                "id": "20:406",
                "name": "Container (margin)",
                "type": "FRAME",
                "scrollBehavior": "SCROLLS",
                "children": [
                  {
                    "id": "20:407",
                    "name": "Text",
                    "type": "FRAME",
                    "scrollBehavior": "SCROLLS",
                    "children": [
                      {
                        "id": "20:408",
                        "name": "密 码",
                        "type": "TEXT",
                        "scrollBehavior": "SCROLLS",
                        "blendMode": "PASS_THROUGH",
                        "fills": [
                          {
                            "opacity": 0.8500000238418579,
                            "blendMode": "NORMAL",
                            "type": "SOLID",
                            "color": {
                              "r": 0.5764706134796143,
                              "g": 0.772549033164978,
                              "b": 0.9921568632125854,
                              "a": 1.0
                            }
                          }
                        ],
                        "strokes": [],
                        "strokeWeight": 1.0,
                        "strokeAlign": "OUTSIDE",
                        "absoluteBoundingBox": {
                          "x": 375.90625,
                          "y": 325.66668701171875,
                          "width": 48.0,
                          "height": 23.0
                        },
                        "absoluteRenderBounds": {
                          "x": 377.521240234375,
                          "y": 327.86669921875,
                          "width": 45.18499755859375,
                          "height": 18.399993896484375
                        },
                        "constraints": {
                          "vertical": "TOP",
                          "horizontal": "LEFT"
                        },
                        "characters": "密 码",
                        "characterStyleOverrides": [],
                        "styleOverrideTable": {},
                        "lineTypes": [
                          "NONE"
                        ],
                        "lineIndentations": [
                          0
                        ],
                        "style": {
                          "fontFamily": "Inter",
                          "fontPostScriptName": null,
                          "fontStyle": "Regular",
                          "fontWeight": 400,
                          "textAutoResize": "WIDTH_AND_HEIGHT",
                          "fontSize": 20.0,
                          "textAlignHorizontal": "RIGHT",
                          "textAlignVertical": "TOP",
                          "letterSpacing": 0.7599999904632568,
                          "lineHeightPx": 22.799999237060547,
                          "lineHeightPercent": 94.19718170166016,
                          "lineHeightPercentFontSize": 114.0,
                          "lineHeightUnit": "PIXELS"
                        },
                        "layoutVersion": 5,
                        "effects": [],
                        "interactions": [],
                        "complexStrokeProperties": {
                          "strokeType": "BASIC"
                        }
                      }
                    ],
                    "blendMode": "PASS_THROUGH",
                    "clipsContent": false,
                    "background": [],
                    "fills": [],
                    "strokes": [],
                    "strokeWeight": 1.0,
                    "strokeAlign": "INSIDE",
                    "backgroundColor": {
                      "r": 0.0,
                      "g": 0.0,
                      "b": 0.0,
                      "a": 0.0
                    },
                    "absoluteBoundingBox": {
                      "x": 363.0,
                      "y": 326.3333435058594,
                      "width": 60.79999923706055,
                      "height": 22.791667938232422
                    },
                    "absoluteRenderBounds": {
                      "x": 363.0,
                      "y": 326.3333435058594,
                      "width": 60.79999923706055,
                      "height": 22.791667938232422
                    },
                    "constraints": {
                      "vertical": "TOP",
                      "horizontal": "LEFT"
                    },
                    "layoutAlign": "INHERIT",
                    "layoutGrow": 0.0,
                    "minWidth": 60.79999923706055,
                    "layoutSizingHorizontal": "FIXED",
                    "layoutSizingVertical": "FIXED",
                    "effects": [],
                    "interactions": [],
                    "complexStrokeProperties": {
                      "strokeType": "BASIC"
                    }
                  },
                  {
                    "id": "20:409",
                    "name": "Container",
                    "type": "FRAME",
                    "scrollBehavior": "SCROLLS",
                    "children": [
                      {
                        "id": "20:410",
                        "name": "Password Input",
                        "type": "FRAME",
                        "scrollBehavior": "SCROLLS",
                        "children": [
                          {
                            "id": "20:411",
                            "name": "请输入密码",
                            "type": "TEXT",
                            "scrollBehavior": "SCROLLS",
                            "blendMode": "PASS_THROUGH",
                            "fills": [
                              {
                                "opacity": 0.25,
                                "blendMode": "NORMAL",
                                "type": "SOLID",
                                "color": {
                                  "r": 0.5568627715110779,
                                  "g": 0.772549033164978,
                                  "b": 1.0,
                                  "a": 1.0
                                }
                              }
                            ],
                            "strokes": [],
                            "strokeWeight": 1.0,
                            "strokeAlign": "OUTSIDE",
                            "absoluteBoundingBox": {
                              "x": 452.4666748046875,
                              "y": 328.2291564941406,
                              "width": 250.86668395996094,
                              "height": 19.0
                            },
                            "absoluteRenderBounds": {
                              "x": 453.138671875,
                              "y": 329.74114990234375,
                              "width": 78.36798095703125,
                              "height": 14.76800537109375
                            },
                            "constraints": {
                              "vertical": "TOP",
                              "horizontal": "LEFT"
                            },
                            "layoutAlign": "STRETCH",
                            "layoutGrow": 0.0,
                            "layoutSizingHorizontal": "FILL",
                            "layoutSizingVertical": "HUG",
                            "characters": "请输入密码",
                            "characterStyleOverrides": [],
                            "styleOverrideTable": {},
                            "lineTypes": [
                              "NONE"
                            ],
                            "lineIndentations": [
                              0
                            ],
                            "style": {
                              "fontFamily": "Inter",
                              "fontPostScriptName": null,
                              "fontStyle": "Regular",
                              "fontWeight": 400,
                              "textAutoResize": "HEIGHT",
                              "fontSize": 16.0,
                              "textAlignHorizontal": "LEFT",
                              "textAlignVertical": "TOP",
                              "letterSpacing": 0.0,
                              "lineHeightPx": 19.363636016845703,
                              "lineHeightPercent": 100.0,
                              "lineHeightUnit": "INTRINSIC_%"
                            },
                            "layoutVersion": 5,
                            "effects": [],
                            "interactions": [],
                            "complexStrokeProperties": {
                              "strokeType": "BASIC"
                            }
                          }
                        ],
                        "blendMode": "PASS_THROUGH",
                        "clipsContent": true,
                        "background": [],
                        "fills": [],
                        "strokes": [],
                        "strokeWeight": 1.0,
                        "strokeAlign": "INSIDE",
                        "backgroundColor": {
                          "r": 0.0,
                          "g": 0.0,
                          "b": 0.0,
                          "a": 0.0
                        },
                        "layoutMode": "VERTICAL",
                        "counterAxisSizingMode": "FIXED",
                        "primaryAxisSizingMode": "FIXED",
                        "primaryAxisAlignItems": "CENTER",
                        "strokesIncludedInLayout": true,
                        "layoutWrap": "NO_WRAP",
                        "absoluteBoundingBox": {
                          "x": 452.4666748046875,
                          "y": 325.7291564941406,
                          "width": 250.86668395996094,
                          "height": 24.0
                        },
                        "absoluteRenderBounds": {
                          "x": 452.4666748046875,
                          "y": 325.7291564941406,
                          "width": 250.86669921875,
                          "height": 24.0
                        },
                        "constraints": {
                          "vertical": "TOP",
                          "horizontal": "LEFT"
                        },
                        "layoutAlign": "INHERIT",
                        "layoutGrow": 250.875,
                        "layoutSizingHorizontal": "FILL",
                        "layoutSizingVertical": "FIXED",
                        "effects": [],
                        "interactions": [],
                        "complexStrokeProperties": {
                          "strokeType": "BASIC"
                        }
                      },
                      {
                        "id": "20:412",
                        "name": "Button",
                        "type": "FRAME",
                        "scrollBehavior": "SCROLLS",
                        "children": [
                          {
                            "id": "20:413",
                            "name": "Icon",
                            "type": "FRAME",
                            "scrollBehavior": "SCROLLS",
                            "children": [
                              {
                                "id": "20:414",
                                "name": "Vector",
                                "type": "VECTOR",
                                "scrollBehavior": "SCROLLS",
                                "blendMode": "PASS_THROUGH",
                                "fills": [],
                                "strokes": [
                                  {
                                    "opacity": 0.44999998807907104,
                                    "blendMode": "NORMAL",
                                    "type": "SOLID",
                                    "color": {
                                      "r": 0.5764706134796143,
                                      "g": 0.772549033164978,
                                      "b": 0.9921568632125854,
                                      "a": 1.0
                                    }
                                  }
                                ],
                                "strokeWeight": 1.25,
                                "strokeAlign": "CENTER",
                                "strokeJoin": "ROUND",
                                "strokeCap": "ROUND",
                                "absoluteBoundingBox": {
                                  "x": 712.5830688476562,
                                  "y": 333.35455322265625,
                                  "width": 12.500631332397461,
                                  "height": 8.749229431152344
                                },
                                "absoluteRenderBounds": {
                                  "x": 711.9580688476562,
                                  "y": 332.72955322265625,
                                  "width": 13.7506103515625,
                                  "height": 9.999237060546875
                                },
                                "constraints": {
                                  "vertical": "SCALE",
                                  "horizontal": "SCALE"
                                },
                                "effects": [],
                                "interactions": [],
                                "complexStrokeProperties": {
                                  "strokeType": "BASIC"
                                }
                              },
                              {
                                "id": "20:415",
                                "name": "Vector",
                                "type": "VECTOR",
                                "scrollBehavior": "SCROLLS",
                                "blendMode": "PASS_THROUGH",
                                "fills": [],
                                "strokes": [
                                  {
                                    "opacity": 0.44999998807907104,
                                    "blendMode": "NORMAL",
                                    "type": "SOLID",
                                    "color": {
                                      "r": 0.5764706134796143,
                                      "g": 0.772549033164978,
                                      "b": 0.9921568632125854,
                                      "a": 1.0
                                    }
                                  }
                                ],
                                "strokeWeight": 1.25,
                                "strokeAlign": "CENTER",
                                "strokeJoin": "ROUND",
                                "strokeCap": "ROUND",
                                "absoluteBoundingBox": {
                                  "x": 716.9583740234375,
                                  "y": 335.8541564941406,
                                  "width": 3.75,
                                  "height": 3.75
                                },
                                "absoluteRenderBounds": {
                                  "x": 716.3333740234375,
                                  "y": 335.2291564941406,
                                  "width": 5.0,
                                  "height": 5.0
                                },
                                "constraints": {
                                  "vertical": "SCALE",
                                  "horizontal": "SCALE"
                                },
                                "effects": [],
                                "interactions": [],
                                "complexStrokeProperties": {
                                  "strokeType": "BASIC"
                                }
                              }
                            ],
                            "blendMode": "PASS_THROUGH",
                            "clipsContent": true,
                            "background": [],
                            "fills": [],
                            "strokes": [],
                            "strokeWeight": 1.0,
                            "strokeAlign": "INSIDE",
                            "backgroundColor": {
                              "r": 0.0,
                              "g": 0.0,
                              "b": 0.0,
                              "a": 0.0
                            },
                            "absoluteBoundingBox": {
                              "x": 711.3333740234375,
                              "y": 330.2291564941406,
                              "width": 15.0,
                              "height": 15.0
                            },
                            "absoluteRenderBounds": {
                              "x": 711.3333740234375,
                              "y": 330.2291564941406,
                              "width": 15.0,
                              "height": 15.0
                            },
                            "constraints": {
                              "vertical": "TOP",
                              "horizontal": "LEFT"
                            },
                            "layoutAlign": "INHERIT",
                            "layoutGrow": 0.0,
                            "layoutSizingHorizontal": "FIXED",
                            "layoutSizingVertical": "FIXED",
                            "effects": [],
                            "interactions": [],
                            "complexStrokeProperties": {
                              "strokeType": "BASIC"
                            }
                          }
                        ],
                        "blendMode": "PASS_THROUGH",
                        "clipsContent": false,
                        "background": [],
                        "fills": [],
                        "strokes": [],
                        "strokeWeight": 1.0,
                        "strokeAlign": "INSIDE",
                        "backgroundColor": {
                          "r": 0.0,
                          "g": 0.0,
                          "b": 0.0,
                          "a": 0.0
                        },
                        "layoutMode": "VERTICAL",
                        "counterAxisSizingMode": "FIXED",
                        "primaryAxisSizingMode": "FIXED",
                        "primaryAxisAlignItems": "CENTER",
                        "paddingLeft": 8.0,
                        "strokesIncludedInLayout": true,
                        "layoutWrap": "NO_WRAP",
                        "absoluteBoundingBox": {
                          "x": 703.3333740234375,
                          "y": 330.2291564941406,
                          "width": 23.0,
                          "height": 15.0
                        },
                        "absoluteRenderBounds": {
                          "x": 703.3333740234375,
                          "y": 330.2291564941406,
                          "width": 23.0,
                          "height": 15.0
                        },
                        "constraints": {
                          "vertical": "TOP",
                          "horizontal": "LEFT"
                        },
                        "layoutAlign": "INHERIT",
                        "layoutGrow": 0.0,
                        "layoutSizingHorizontal": "FIXED",
                        "layoutSizingVertical": "FIXED",
                        "effects": [],
                        "interactions": [],
                        "complexStrokeProperties": {
                          "strokeType": "BASIC"
                        }
                      }
                    ],
                    "blendMode": "PASS_THROUGH",
                    "clipsContent": false,
                    "background": [
                      {
                        "opacity": 0.25,
                        "blendMode": "NORMAL",
                        "type": "SOLID",
                        "color": {
                          "r": 0.03921568766236305,
                          "g": 0.11764705926179886,
                          "b": 0.27450981736183167,
                          "a": 1.0
                        }
                      }
                    ],
                    "fills": [
                      {
                        "opacity": 0.25,
                        "blendMode": "NORMAL",
                        "type": "SOLID",
                        "color": {
                          "r": 0.03921568766236305,
                          "g": 0.11764705926179886,
                          "b": 0.27450981736183167,
                          "a": 1.0
                        }
                      }
                    ],
                    "strokes": [
                      {
                        "opacity": 0.44999998807907104,
                        "blendMode": "NORMAL",
                        "type": "SOLID",
                        "color": {
                          "r": 0.21960784494876862,
                          "g": 0.545098066329956,
                          "b": 0.9921568632125854,
                          "a": 1.0
                        }
                      }
                    ],
                    "cornerRadius": 10.0,
                    "cornerSmoothing": 0.0,
                    "strokeWeight": 0.6666669845581055,
                    "strokeAlign": "INSIDE",
                    "backgroundColor": {
                      "r": 0.03921568766236305,
                      "g": 0.11764705926179886,
                      "b": 0.27450981736183167,
                      "a": 0.25
                    },
                    "layoutMode": "HORIZONTAL",
                    "primaryAxisSizingMode": "FIXED",
                    "counterAxisAlignItems": "CENTER",
                    "paddingLeft": 16.0,
                    "paddingRight": 16.0,
                    "paddingTop": 16.0,
                    "paddingBottom": 16.0,
                    "strokesIncludedInLayout": true,
                    "layoutWrap": "NO_WRAP",
                    "absoluteBoundingBox": {
                      "x": 435.79998779296875,
                      "y": 309.0625,
                      "width": 307.20001220703125,
                      "height": 57.333335876464844
                    },
                    "absoluteRenderBounds": {
                      "x": 427.79998779296875,
                      "y": 301.0625,
                      "width": 323.20001220703125,
                      "height": 73.33334350585938
                    },
                    "constraints": {
                      "vertical": "TOP",
                      "horizontal": "LEFT"
                    },
                    "layoutAlign": "INHERIT",
                    "layoutGrow": 307.2083435058594,
                    "layoutSizingHorizontal": "FILL",
                    "layoutSizingVertical": "HUG",
                    "effects": [
                      {
                        "type": "INNER_SHADOW",
                        "visible": true,
                        "color": {
                          "r": 0.21960784494876862,
                          "g": 0.545098066329956,
                          "b": 0.9921568632125854,
                          "a": 0.05000000074505806
                        },
                        "blendMode": "NORMAL",
                        "offset": {
                          "x": 0.0,
                          "y": 0.0
                        },
                        "radius": 12.0
                      },
                      {
                        "type": "DROP_SHADOW",
                        "visible": true,
                        "color": {
                          "r": 0.21960784494876862,
                          "g": 0.545098066329956,
                          "b": 0.9921568632125854,
                          "a": 0.11999999731779099
                        },
                        "blendMode": "NORMAL",
                        "offset": {
                          "x": 0.0,
                          "y": 0.0
                        },
                        "radius": 8.0,
                        "showShadowBehindNode": false
                      }
                    ],
                    "interactions": [],
                    "complexStrokeProperties": {
                      "strokeType": "BASIC"
                    }
                  }
                ],
                "blendMode": "PASS_THROUGH",
                "clipsContent": false,
                "background": [],
                "fills": [],
                "strokes": [],
                "strokeWeight": 1.0,
                "strokeAlign": "INSIDE",
                "backgroundColor": {
                  "r": 0.0,
                  "g": 0.0,
                  "b": 0.0,
                  "a": 0.0
                },
                "layoutMode": "HORIZONTAL",
                "primaryAxisSizingMode": "FIXED",
                "counterAxisAlignItems": "CENTER",
                "paddingTop": 28.0,
                "strokesIncludedInLayout": true,
                "itemSpacing": 12.0,
                "layoutWrap": "NO_WRAP",
                "absoluteBoundingBox": {
                  "x": 363.0,
                  "y": 281.0625,
                  "width": 380.0,
                  "height": 85.33333587646484
                },
                "absoluteRenderBounds": {
                  "x": 363.0,
                  "y": 281.0625,
                  "width": 388.0,
                  "height": 93.33334350585938
                },
                "constraints": {
                  "vertical": "TOP",
                  "horizontal": "LEFT"
                },
                "layoutAlign": "INHERIT",
                "layoutGrow": 0.0,
                "layoutSizingHorizontal": "FIXED",
                "layoutSizingVertical": "HUG",
                "effects": [],
                "interactions": [],
                "complexStrokeProperties": {
                  "strokeType": "BASIC"
                }
              },
              {
                "id": "20:416",
                "name": "Container (margin)",
                "type": "FRAME",
                "scrollBehavior": "SCROLLS",
                "children": [
                  {
                    "id": "20:417",
                    "name": "Text",
                    "type": "FRAME",
                    "scrollBehavior": "SCROLLS",
                    "children": [
                      {
                        "id": "20:418",
                        "name": "动态码",
                        "type": "TEXT",
                        "scrollBehavior": "SCROLLS",
                        "blendMode": "PASS_THROUGH",
                        "fills": [
                          {
                            "opacity": 0.8500000238418579,
                            "blendMode": "NORMAL",
                            "type": "SOLID",
                            "color": {
                              "r": 0.5764706134796143,
                              "g": 0.772549033164978,
                              "b": 0.9921568632125854,
                              "a": 1.0
                            }
                          }
                        ],
                        "strokes": [],
                        "strokeWeight": 1.0,
                        "strokeAlign": "OUTSIDE",
                        "absoluteBoundingBox": {
                          "x": 361.90625,
                          "y": 411.0,
                          "width": 62.0,
                          "height": 23.0
                        },
                        "absoluteRenderBounds": {
                          "x": 363.46624755859375,
                          "y": 413.1199951171875,
                          "width": 59.239990234375,
                          "height": 18.459991455078125
                        },
                        "constraints": {
                          "vertical": "TOP",
                          "horizontal": "LEFT"
                        },
                        "characters": "动态码",
                        "characterStyleOverrides": [],
                        "styleOverrideTable": {},
                        "lineTypes": [
                          "NONE"
                        ],
                        "lineIndentations": [
                          0
                        ],
                        "style": {
                          "fontFamily": "Inter",
                          "fontPostScriptName": null,
                          "fontStyle": "Regular",
                          "fontWeight": 400,
                          "textAutoResize": "WIDTH_AND_HEIGHT",
                          "fontSize": 20.0,
                          "textAlignHorizontal": "RIGHT",
                          "textAlignVertical": "TOP",
                          "letterSpacing": 0.7599999904632568,
                          "lineHeightPx": 22.799999237060547,
                          "lineHeightPercent": 94.19718170166016,
                          "lineHeightPercentFontSize": 114.0,
                          "lineHeightUnit": "PIXELS"
                        },
                        "layoutVersion": 5,
                        "effects": [],
                        "interactions": [],
                        "complexStrokeProperties": {
                          "strokeType": "BASIC"
                        }
                      }
                    ],
                    "blendMode": "PASS_THROUGH",
                    "clipsContent": false,
                    "background": [],
                    "fills": [],
                    "strokes": [],
                    "strokeWeight": 1.0,
                    "strokeAlign": "INSIDE",
                    "backgroundColor": {
                      "r": 0.0,
                      "g": 0.0,
                      "b": 0.0,
                      "a": 0.0
                    },
                    "absoluteBoundingBox": {
                      "x": 363.0,
                      "y": 411.66668701171875,
                      "width": 60.79999923706055,
                      "height": 22.791667938232422
                    },
                    "absoluteRenderBounds": {
                      "x": 363.0,
                      "y": 411.66668701171875,
                      "width": 60.79999923706055,
                      "height": 22.791667938232422
                    },
                    "constraints": {
                      "vertical": "TOP",
                      "horizontal": "LEFT"
                    },
                    "layoutAlign": "INHERIT",
                    "layoutGrow": 0.0,
                    "minWidth": 60.79999923706055,
                    "layoutSizingHorizontal": "FIXED",
                    "layoutSizingVertical": "FIXED",
                    "effects": [],
                    "interactions": [],
                    "complexStrokeProperties": {
                      "strokeType": "BASIC"
                    }
                  },
                  {
                    "id": "20:419",
                    "name": "Container",
                    "type": "FRAME",
                    "scrollBehavior": "SCROLLS",
                    "children": [
                      {
                        "id": "20:420",
                        "name": "Text Input",
                        "type": "FRAME",
                        "scrollBehavior": "SCROLLS",
                        "children": [
                          {
                            "id": "20:421",
                            "name": "请输入动态码",
                            "type": "TEXT",
                            "scrollBehavior": "SCROLLS",
                            "blendMode": "PASS_THROUGH",
                            "fills": [
                              {
                                "opacity": 0.25,
                                "blendMode": "NORMAL",
                                "type": "SOLID",
                                "color": {
                                  "r": 0.5568627715110779,
                                  "g": 0.772549033164978,
                                  "b": 1.0,
                                  "a": 1.0
                                }
                              }
                            ],
                            "strokes": [],
                            "strokeWeight": 1.0,
                            "strokeAlign": "OUTSIDE",
                            "absoluteBoundingBox": {
                              "x": 452.4666442871094,
                              "y": 413.5625,
                              "width": 273.8666687011719,
                              "height": 19.0
                            },
                            "absoluteRenderBounds": {
                              "x": 453.1386413574219,
                              "y": 415.0585021972656,
                              "width": 102.36801147460938,
                              "height": 14.76800537109375
                            },
                            "constraints": {
                              "vertical": "TOP",
                              "horizontal": "LEFT"
                            },
                            "layoutAlign": "STRETCH",
                            "layoutGrow": 0.0,
                            "layoutSizingHorizontal": "FILL",
                            "layoutSizingVertical": "HUG",
                            "characters": "请输入动态码",
                            "characterStyleOverrides": [],
                            "styleOverrideTable": {},
                            "lineTypes": [
                              "NONE"
                            ],
                            "lineIndentations": [
                              0
                            ],
                            "style": {
                              "fontFamily": "Inter",
                              "fontPostScriptName": null,
                              "fontStyle": "Regular",
                              "fontWeight": 400,
                              "textAutoResize": "HEIGHT",
                              "fontSize": 16.0,
                              "textAlignHorizontal": "LEFT",
                              "textAlignVertical": "TOP",
                              "letterSpacing": 1.600000023841858,
                              "lineHeightPx": 19.363636016845703,
                              "lineHeightPercent": 100.0,
                              "lineHeightUnit": "INTRINSIC_%"
                            },
                            "layoutVersion": 5,
                            "effects": [],
                            "interactions": [],
                            "complexStrokeProperties": {
                              "strokeType": "BASIC"
                            }
                          }
                        ],
                        "blendMode": "PASS_THROUGH",
                        "clipsContent": true,
                        "background": [],
                        "fills": [],
                        "strokes": [],
                        "strokeWeight": 1.0,
                        "strokeAlign": "INSIDE",
                        "backgroundColor": {
                          "r": 0.0,
                          "g": 0.0,
                          "b": 0.0,
                          "a": 0.0
                        },
                        "layoutMode": "VERTICAL",
                        "counterAxisSizingMode": "FIXED",
                        "primaryAxisSizingMode": "FIXED",
                        "primaryAxisAlignItems": "CENTER",
                        "strokesIncludedInLayout": true,
                        "layoutWrap": "NO_WRAP",
                        "absoluteBoundingBox": {
                          "x": 452.4666442871094,
                          "y": 411.0625,
                          "width": 273.8666687011719,
                          "height": 24.0
                        },
                        "absoluteRenderBounds": {
                          "x": 452.4666442871094,
                          "y": 411.0625,
                          "width": 273.8666687011719,
                          "height": 24.0
                        },
                        "constraints": {
                          "vertical": "TOP",
                          "horizontal": "LEFT"
                        },
                        "layoutAlign": "INHERIT",
                        "layoutGrow": 273.875,
                        "layoutSizingHorizontal": "FILL",
                        "layoutSizingVertical": "FIXED",
                        "effects": [],
                        "interactions": [],
                        "complexStrokeProperties": {
                          "strokeType": "BASIC"
                        }
                      }
                    ],
                    "blendMode": "PASS_THROUGH",
                    "clipsContent": false,
                    "background": [
                      {
                        "opacity": 0.25,
                        "blendMode": "NORMAL",
                        "type": "SOLID",
                        "color": {
                          "r": 0.03921568766236305,
                          "g": 0.11764705926179886,
                          "b": 0.27450981736183167,
                          "a": 1.0
                        }
                      }
                    ],
                    "fills": [
                      {
                        "opacity": 0.25,
                        "blendMode": "NORMAL",
                        "type": "SOLID",
                        "color": {
                          "r": 0.03921568766236305,
                          "g": 0.11764705926179886,
                          "b": 0.27450981736183167,
                          "a": 1.0
                        }
                      }
                    ],
                    "strokes": [
                      {
                        "opacity": 0.44999998807907104,
                        "blendMode": "NORMAL",
                        "type": "SOLID",
                        "color": {
                          "r": 0.21960784494876862,
                          "g": 0.545098066329956,
                          "b": 0.9921568632125854,
                          "a": 1.0
                        }
                      }
                    ],
                    "cornerRadius": 10.0,
                    "cornerSmoothing": 0.0,
                    "strokeWeight": 0.6666669845581055,
                    "strokeAlign": "INSIDE",
                    "backgroundColor": {
                      "r": 0.03921568766236305,
                      "g": 0.11764705926179886,
                      "b": 0.27450981736183167,
                      "a": 0.25
                    },
                    "layoutMode": "HORIZONTAL",
                    "primaryAxisSizingMode": "FIXED",
                    "counterAxisAlignItems": "CENTER",
                    "paddingLeft": 16.0,
                    "paddingRight": 16.0,
                    "paddingTop": 16.0,
                    "paddingBottom": 16.0,
                    "strokesIncludedInLayout": true,
                    "layoutWrap": "NO_WRAP",
                    "absoluteBoundingBox": {
                      "x": 435.79998779296875,
                      "y": 394.3958435058594,
                      "width": 307.20001220703125,
                      "height": 57.333335876464844
                    },
                    "absoluteRenderBounds": {
                      "x": 427.79998779296875,
                      "y": 386.3958435058594,
                      "width": 323.20001220703125,
                      "height": 73.33334350585938
                    },
                    "constraints": {
                      "vertical": "TOP",
                      "horizontal": "LEFT"
                    },
                    "layoutAlign": "INHERIT",
                    "layoutGrow": 307.2083435058594,
                    "layoutSizingHorizontal": "FILL",
                    "layoutSizingVertical": "HUG",
                    "effects": [
                      {
                        "type": "INNER_SHADOW",
                        "visible": true,
                        "color": {
                          "r": 0.21960784494876862,
                          "g": 0.545098066329956,
                          "b": 0.9921568632125854,
                          "a": 0.05000000074505806
                        },
                        "blendMode": "NORMAL",
                        "offset": {
                          "x": 0.0,
                          "y": 0.0
                        },
                        "radius": 12.0
                      },
                      {
                        "type": "DROP_SHADOW",
                        "visible": true,
                        "color": {
                          "r": 0.21960784494876862,
                          "g": 0.545098066329956,
                          "b": 0.9921568632125854,
                          "a": 0.11999999731779099
                        },
                        "blendMode": "NORMAL",
                        "offset": {
                          "x": 0.0,
                          "y": 0.0
                        },
                        "radius": 8.0,
                        "showShadowBehindNode": false
                      }
                    ],
                    "interactions": [],
                    "complexStrokeProperties": {
                      "strokeType": "BASIC"
                    }
                  }
                ],
                "blendMode": "PASS_THROUGH",
                "clipsContent": false,
                "background": [],
                "fills": [],
                "strokes": [],
                "strokeWeight": 1.0,
                "strokeAlign": "INSIDE",
                "backgroundColor": {
                  "r": 0.0,
                  "g": 0.0,
                  "b": 0.0,
                  "a": 0.0
                },
                "layoutMode": "HORIZONTAL",
                "primaryAxisSizingMode": "FIXED",
                "counterAxisAlignItems": "CENTER",
                "paddingTop": 28.0,
                "strokesIncludedInLayout": true,
                "itemSpacing": 12.0,
                "layoutWrap": "NO_WRAP",
                "absoluteBoundingBox": {
                  "x": 363.0,
                  "y": 366.3958435058594,
                  "width": 380.0,
                  "height": 85.33333587646484
                },
                "absoluteRenderBounds": {
                  "x": 363.0,
                  "y": 366.3958435058594,
                  "width": 388.0,
                  "height": 93.33334350585938
                },
                "constraints": {
                  "vertical": "TOP",
                  "horizontal": "LEFT"
                },
                "layoutAlign": "INHERIT",
                "layoutGrow": 0.0,
                "layoutSizingHorizontal": "FIXED",
                "layoutSizingVertical": "HUG",
                "effects": [],
                "interactions": [],
                "complexStrokeProperties": {
                  "strokeType": "BASIC"
                }
              },
              {
                "id": "20:422",
                "name": "Container (margin)",
                "type": "FRAME",
                "scrollBehavior": "SCROLLS",
                "children": [
                  {
                    "id": "20:423",
                    "name": "Button",
                    "type": "FRAME",
                    "scrollBehavior": "SCROLLS",
                    "children": [
                      {
                        "id": "20:424",
                        "name": "登 录",
                        "type": "TEXT",
                        "scrollBehavior": "SCROLLS",
                        "blendMode": "PASS_THROUGH",
                        "fills": [
                          {
                            "blendMode": "NORMAL",
                            "type": "SOLID",
                            "color": {
                              "r": 0.658823549747467,
                              "g": 0.8313725590705872,
                              "b": 1.0,
                              "a": 1.0
                            }
                          }
                        ],
                        "strokes": [],
                        "strokeWeight": 1.0,
                        "strokeAlign": "OUTSIDE",
                        "absoluteBoundingBox": {
                          "x": 527.5,
                          "y": 513.9948120117188,
                          "width": 51.0,
                          "height": 26.0
                        },
                        "absoluteRenderBounds": {
                          "x": 528.0015258789062,
                          "y": 517.0748291015625,
                          "width": 49.4569091796875,
                          "height": 18.79998779296875
                        },
                        "constraints": {
                          "vertical": "TOP",
                          "horizontal": "LEFT"
                        },
                        "layoutAlign": "INHERIT",
                        "layoutGrow": 0.0,
                        "layoutSizingHorizontal": "HUG",
                        "layoutSizingVertical": "HUG",
                        "characters": "登 录",
                        "characterStyleOverrides": [],
                        "styleOverrideTable": {},
                        "lineTypes": [
                          "NONE"
                        ],
                        "lineIndentations": [
                          0
                        ],
                        "style": {
                          "fontFamily": "Inter",
                          "fontPostScriptName": null,
                          "fontStyle": "Bold",
                          "fontWeight": 700,
                          "textAutoResize": "WIDTH_AND_HEIGHT",
                          "fontSize": 20.0,
                          "textAlignHorizontal": "CENTER",
                          "textAlignVertical": "TOP",
                          "letterSpacing": 3.0239999294281006,
                          "lineHeightPx": 25.200000762939453,
                          "lineHeightPercent": 104.11268615722656,
                          "lineHeightPercentFontSize": 126.0,
                          "lineHeightUnit": "PIXELS"
                        },
                        "layoutVersion": 5,
                        "effects": [],
                        "interactions": [],
                        "complexStrokeProperties": {
                          "strokeType": "BASIC"
                        }
                      }
                    ],
                    "blendMode": "PASS_THROUGH",
                    "clipsContent": true,
                    "background": [
                      {
                        "opacity": 0.30000001192092896,
                        "blendMode": "NORMAL",
                        "type": "SOLID",
                        "color": {
                          "r": 0.0784313753247261,
                          "g": 0.23529411852359772,
                          "b": 0.6274510025978088,
                          "a": 1.0
                        }
                      }
                    ],
                    "fills": [
                      {
                        "opacity": 0.30000001192092896,
                        "blendMode": "NORMAL",
                        "type": "SOLID",
                        "color": {
                          "r": 0.0784313753247261,
                          "g": 0.23529411852359772,
                          "b": 0.6274510025978088,
                          "a": 1.0
                        }
                      }
                    ],
                    "strokes": [
                      {
                        "opacity": 0.550000011920929,
                        "blendMode": "NORMAL",
                        "type": "SOLID",
                        "color": {
                          "r": 0.21960784494876862,
                          "g": 0.545098066329956,
                          "b": 0.9921568632125854,
                          "a": 1.0
                        }
                      }
                    ],
                    "cornerRadius": 16.0,
                    "cornerSmoothing": 0.0,
                    "strokeWeight": 0.6666669845581055,
                    "strokeAlign": "INSIDE",
                    "backgroundColor": {
                      "r": 0.0784313753247261,
                      "g": 0.23529411852359772,
                      "b": 0.6274510025978088,
                      "a": 0.30000001192092896
                    },
                    "layoutMode": "VERTICAL",
                    "counterAxisSizingMode": "FIXED",
                    "primaryAxisSizingMode": "FIXED",
                    "counterAxisAlignItems": "CENTER",
                    "primaryAxisAlignItems": "CENTER",
                    "paddingTop": 14.0,
                    "paddingBottom": 14.0,
                    "strokesIncludedInLayout": true,
                    "layoutWrap": "NO_WRAP",
                    "absoluteBoundingBox": {
                      "x": 403.0,
                      "y": 499.72918701171875,
                      "width": 300.0,
                      "height": 54.53125
                    },
                    "absoluteRenderBounds": {
                      "x": 387.0,
                      "y": 483.72918701171875,
                      "width": 332.0,
                      "height": 86.53125
                    },
                    "constraints": {
                      "vertical": "TOP",
                      "horizontal": "LEFT"
                    },
                    "layoutAlign": "STRETCH",
                    "layoutGrow": 0.0,
                    "layoutSizingHorizontal": "FIXED",
                    "layoutSizingVertical": "FILL",
                    "effects": [
                      {
                        "type": "INNER_SHADOW",
                        "visible": true,
                        "color": {
                          "r": 0.21960784494876862,
                          "g": 0.545098066329956,
                          "b": 0.9921568632125854,
                          "a": 0.07999999821186066
                        },
                        "blendMode": "NORMAL",
                        "offset": {
                          "x": 0.0,
                          "y": 0.0
                        },
                        "radius": 20.0
                      },
                      {
                        "type": "DROP_SHADOW",
                        "visible": true,
                        "color": {
                          "r": 0.21960784494876862,
                          "g": 0.545098066329956,
                          "b": 0.9921568632125854,
                          "a": 0.30000001192092896
                        },
                        "blendMode": "NORMAL",
                        "offset": {
                          "x": 0.0,
                          "y": 0.0
                        },
                        "radius": 16.0,
                        "showShadowBehindNode": false
                      }
                    ],
                    "interactions": [],
                    "complexStrokeProperties": {
                      "strokeType": "BASIC"
                    }
                  }
                ],
                "blendMode": "PASS_THROUGH",
                "clipsContent": false,
                "background": [],
                "fills": [],
                "strokes": [],
                "strokeWeight": 1.0,
                "strokeAlign": "INSIDE",
                "backgroundColor": {
                  "r": 0.0,
                  "g": 0.0,
                  "b": 0.0,
                  "a": 0.0
                },
                "layoutMode": "HORIZONTAL",
                "counterAxisSizingMode": "FIXED",
                "primaryAxisSizingMode": "FIXED",
                "primaryAxisAlignItems": "CENTER",
                "paddingTop": 48.0,
                "strokesIncludedInLayout": true,
                "layoutWrap": "NO_WRAP",
                "absoluteBoundingBox": {
                  "x": 363.0,
                  "y": 451.72918701171875,
                  "width": 380.0,
                  "height": 102.53125
                },
                "absoluteRenderBounds": {
                  "x": 363.0,
                  "y": 451.72918701171875,
                  "width": 380.0,
                  "height": 118.53125
                },
                "constraints": {
                  "vertical": "TOP",
                  "horizontal": "LEFT"
                },
                "layoutAlign": "INHERIT",
                "layoutGrow": 0.0,
                "layoutSizingHorizontal": "FIXED",
                "layoutSizingVertical": "FIXED",
                "effects": [],
                "interactions": [],
                "complexStrokeProperties": {
                  "strokeType": "BASIC"
                }
              }
            ],
            "blendMode": "PASS_THROUGH",
            "clipsContent": false,
            "background": [],
            "fills": [],
            "strokes": [],
            "strokeWeight": 1.0,
            "strokeAlign": "INSIDE",
            "backgroundColor": {
              "r": 0.0,
              "g": 0.0,
              "b": 0.0,
              "a": 0.0
            },
            "layoutMode": "VERTICAL",
            "counterAxisSizingMode": "FIXED",
            "paddingLeft": 40.0,
            "paddingRight": 40.0,
            "paddingTop": 40.0,
            "paddingBottom": 40.0,
            "strokesIncludedInLayout": true,
            "layoutWrap": "NO_WRAP",
            "absoluteBoundingBox": {
              "x": 323.0,
              "y": 183.7291717529297,
              "width": 460.0,
              "height": 410.53125
            },
            "absoluteRenderBounds": {
              "x": 323.0,
              "y": 183.7291717529297,
              "width": 460.0,
              "height": 410.53125
            },
            "constraints": {
              "vertical": "TOP",
              "horizontal": "LEFT"
            },
            "layoutSizingHorizontal": "FIXED",
            "layoutSizingVertical": "HUG",
            "effects": [],
            "interactions": [],
            "complexStrokeProperties": {
              "strokeType": "BASIC"
            }
          }
        ],
        "blendMode": "PASS_THROUGH",
        "clipsContent": true,
        "background": [
          {
            "blendMode": "NORMAL",
            "type": "SOLID",
            "color": {
              "r": 0.03921568766236305,
              "g": 0.06666667014360428,
              "b": 0.0941176488995552,
              "a": 1.0
            }
          }
        ],
        "fills": [
          {
            "blendMode": "NORMAL",
            "type": "SOLID",
            "color": {
              "r": 0.03921568766236305,
              "g": 0.06666667014360428,
              "b": 0.0941176488995552,
              "a": 1.0
            }
          }
        ],
        "strokes": [],
        "cornerRadius": 16.0,
        "cornerSmoothing": 0.0,
        "strokeWeight": 1.0,
        "strokeAlign": "INSIDE",
        "backgroundColor": {
          "r": 0.03921568766236305,
          "g": 0.06666667014360428,
          "b": 0.0941176488995552,
          "a": 1.0
        },
        "absoluteBoundingBox": {
          "x": 0.0,
          "y": 0.0,
          "width": 1106.0,
          "height": 778.0
        },
        "absoluteRenderBounds": {
          "x": -64.0,
          "y": -40.0,
          "width": 1234.0,
          "height": 906.0
        },
        "constraints": {
          "vertical": "TOP",
          "horizontal": "LEFT"
        },
        "layoutAlign": "INHERIT",
        "layoutGrow": 0.0,
        "layoutSizingHorizontal": "FIXED",
        "layoutSizingVertical": "FIXED",
        "effects": [
          {
            "type": "DROP_SHADOW",
            "visible": true,
            "color": {
              "r": 0.0,
              "g": 0.0,
              "b": 0.0,
              "a": 0.800000011920929
            },
            "blendMode": "NORMAL",
            "offset": {
              "x": 0.0,
              "y": 24.0
            },
            "radius": 64.0,
            "showShadowBehindNode": false
          }
        ],
        "interactions": [],
        "complexStrokeProperties": {
          "strokeType": "BASIC"
        }
      }
    ],
    "blendMode": "PASS_THROUGH",
    "clipsContent": false,
    "background": [],
    "fills": [],
    "strokes": [],
    "strokeWeight": 1.0,
    "strokeAlign": "INSIDE",
    "backgroundColor": {
      "r": 0.0,
      "g": 0.0,
      "b": 0.0,
      "a": 0.0
    },
    "layoutMode": "VERTICAL",
    "counterAxisSizingMode": "FIXED",
    "primaryAxisSizingMode": "FIXED",
    "strokesIncludedInLayout": true,
    "layoutWrap": "NO_WRAP",
    "absoluteBoundingBox": {
      "x": 0.0,
      "y": 0.0,
      "width": 1337.3333740234375,
      "height": 931.3333740234375
    },
    "absoluteRenderBounds": {
      "x": -64.0,
      "y": -40.0,
      "width": 1401.3333740234375,
      "height": 971.3333740234375
    },
    "constraints": {
      "vertical": "TOP",
      "horizontal": "LEFT"
    },
    "layoutAlign": "INHERIT",
    "layoutGrow": 0.0,
    "layoutSizingHorizontal": "FIXED",
    "layoutSizingVertical": "FIXED",
    "effects": [],
    "interactions": [],
    "complexStrokeProperties": {
      "strokeType": "BASIC"
    }
  },
  "components": {},
  "componentSets": {},
  "schemaVersion": 0,
  "styles": {}
}